linear_reg.py
linear_reg-0.0.1.dist-info/METADATA
linear_reg-0.0.1.dist-info/WHEEL
linear_reg-0.0.1.dist-info/top_level.txt
linear_reg-0.0.1.dist-info/RECORD
